{
  "affixes": [
    {
      "family_key": "SanctumKeyUpgradeChance",
      "id": 540,
      "identifier": "sanctum_chance_to_upgrade_key_on_floor_completed",
      "kind": "prefix",
      "template": "#% chance for each of your Keys to upgrade on completing a Floor",
      "tiers": [
        {
          "drop_chance": 0,
          "level": 1,
          "name": "Enhancing",
          "text": "(3—4)% chance for each of your Keys to upgrade on completing a Floor"
        },
        {
          "drop_chance": 0,
          "level": 60,
          "name": "Reforging",
          "text": "(5—6)% chance for each of your Keys to upgrade on completing a Floor"
        },
        {
          "drop_chance": 0,
          "level": 77,
          "name": "Upgrading",
          "text": "(7—9)% chance for each of your Keys to upgrade on completing a Floor"
        }
      ]
    },
    {
      "family_key": "SanctumChanceToPreventHonourDeath",
      "id": 539,
      "identifier": "sanctum_chance_to_prevent_zero_honour",
      "kind": "prefix",
      "template": "#% chance if you were to lose all your Honour to have # Honour instead",
      "tiers": [
        {
          "drop_chance": 0,
          "level": 1,
          "name": "Cheater's",
          "text": "(5—8)% chance if you were to lose all your Honour to have 1 Honour instead"
        },
        {
          "drop_chance": 0,
          "level": 75,
          "name": "Deceiver's",
          "text": "(9—12)% chance if you were to lose all your Honour to have 1 Honour instead"
        }
      ]
    },
    {
      "family_key": "SanctumMonstersReducedDamage",
      "id": 532,
      "identifier": "map_monsters_damage_+%",
      "kind": "prefix",
      "template": "Monsters deal # reduced Damage",
      "tiers": [
        {
          "drop_chance": 0,
          "level": 1,
          "name": "Resilient",
          "text": "Monsters deal 6% reduced Damage"
        }
      ]
    },
    {
      "family_key": "SanctumMonstersReducedDamage",
      "id": 533,
      "identifier": "map_monsters_damage",
      "kind": "prefix",
      "template": "Monsters deal #% reduced Damage",
      "tiers": [
        {
          "drop_chance": 0,
          "level": 56,
          "name": "Fortified",
          "text": "Monsters deal (7—8)% reduced Damage"
        },
        {
          "drop_chance": 0,
          "level": 77,
          "name": "Impenetrable",
          "text": "Monsters deal (9—12)% reduced Damage"
        }
      ]
    },
    {
      "family_key": "SanctumMonsterSpeed",
      "id": 536,
      "identifier": "map_monster_attack_cast_and_movement_speed_+%",
      "kind": "prefix",
      "template": "Monsters have # reduced Attack, Cast and Movement Speed",
      "tiers": [
        {
          "drop_chance": 0,
          "level": 1,
          "name": "Time-warping",
          "text": "Monsters have 4% reduced Attack, Cast and Movement Speed"
        },
        {
          "drop_chance": 0,
          "level": 60,
          "name": "Chronomancy",
          "text": "Monsters have 5% reduced Attack, Cast and Movement Speed"
        }
      ]
    },
    {
      "family_key": "SanctumMonsterSpeed",
      "id": 537,
      "identifier": "map_monster_attack_cast_and_movement_speed",
      "kind": "prefix",
      "template": "Monsters have #% reduced Attack, Cast and Movement Speed",
      "tiers": [
        {
          "drop_chance": 0,
          "level": 78,
          "name": "Temporal",
          "text": "Monsters have (6—7)% reduced Attack, Cast and Movement Speed"
        }
      ]
    },
    {
      "family_key": "SanctumMonstersIncreasedDamageTaken",
      "id": 531,
      "identifier": "map_monster_damage_taken",
      "kind": "prefix",
      "template": "Monsters take #% increased Damage",
      "tiers": [
        {
          "drop_chance": 0,
          "level": 1,
          "name": "Crushing",
          "text": "Monsters take (11—15)% increased Damage"
        },
        {
          "drop_chance": 0,
          "level": 56,
          "name": "Punishing",
          "text": "Monsters take (16—20)% increased Damage"
        },
        {
          "drop_chance": 0,
          "level": 77,
          "name": "Annihilating",
          "text": "Monsters take (21—30)% increased Damage"
        }
      ]
    },
    {
      "family_key": "SanctumAdditionalKeyChance",
      "id": 534,
      "identifier": "sanctum_additional_key_chance",
      "kind": "prefix",
      "template": "When you gain a Key #% chance to gain another",
      "tiers": [
        {
          "drop_chance": 0,
          "level": 1,
          "name": "Pilferer's",
          "text": "When you gain a Key (7—9)% chance to gain another"
        },
        {
          "drop_chance": 0,
          "level": 60,
          "name": "Picklock's",
          "text": "When you gain a Key (10—12)% chance to gain another"
        },
        {
          "drop_chance": 0,
          "level": 78,
          "name": "Thief's",
          "text": "When you gain a Key (13—16)% chance to gain another"
        }
      ]
    },
    {
      "family_key": "SanctumRevealExtraRoomEachFloor",
      "id": 520,
      "identifier": "sanctum_map_reveal_extra_room_each_floor",
      "kind": "suffix",
      "template": "# additional Rooms are revealed on the Trial Map",
      "tiers": [
        {
          "drop_chance": 0,
          "level": 1,
          "name": "of Illumination",
          "text": "(2—3) additional Rooms are revealed on the Trial Map"
        },
        {
          "drop_chance": 0,
          "level": 76,
          "name": "of Clairvoyance",
          "text": "4 additional Rooms are revealed on the Trial Map"
        }
      ]
    },
    {
      "family_key": "SanctumAvoidAfflictionChance",
      "id": 530,
      "identifier": "sanctum_avoid_affliction_chance",
      "kind": "suffix",
      "template": "#% chance to Avoid gaining an Affliction",
      "tiers": [
        {
          "drop_chance": 0,
          "level": 1,
          "name": "of Dignity",
          "text": "(6—7)% chance to Avoid gaining an Affliction"
        },
        {
          "drop_chance": 0,
          "level": 55,
          "name": "of Prestige",
          "text": "(8—9)% chance to Avoid gaining an Affliction"
        },
        {
          "drop_chance": 0,
          "level": 69,
          "name": "of Glory",
          "text": "(10—11)% chance to Avoid gaining an Affliction"
        },
        {
          "drop_chance": 0,
          "level": 78,
          "name": "of Honour",
          "text": "(12—15)% chance to Avoid gaining an Affliction"
        }
      ]
    },
    {
      "family_key": "SanctumMaximumHonourResistance",
      "id": 538,
      "identifier": "sanctum_additional_max_honour_resistance",
      "kind": "suffix",
      "template": "+#% to Maximum Honour Resistance",
      "tiers": [
        {
          "drop_chance": 0,
          "level": 60,
          "name": "of Excellence",
          "text": "+(2—3)% to Maximum Honour Resistance"
        },
        {
          "drop_chance": 0,
          "level": 78,
          "name": "of Brilliance",
          "text": "+(4—5)% to Maximum Honour Resistance"
        }
      ]
    },
    {
      "family_key": "SanctumGoldOnRoomCompletion",
      "id": 528,
      "identifier": "gain_x_sanctum_gold_on_room_completion",
      "kind": "suffix",
      "template": "Gain # Sacred Water when you complete a Room",
      "tiers": [
        {
          "drop_chance": 0,
          "level": 1,
          "name": "of the Well",
          "text": "Gain (11—15) Sacred Water when you complete a Room"
        },
        {
          "drop_chance": 0,
          "level": 56,
          "name": "of the Fountain",
          "text": "Gain (16—20) Sacred Water when you complete a Room"
        },
        {
          "drop_chance": 0,
          "level": 77,
          "name": "of the Oasis",
          "text": "Gain (21—30) Sacred Water when you complete a Room"
        }
      ]
    },
    {
      "family_key": "SanctumHonourOnGainKey",
      "id": 535,
      "identifier": "sanctum_restore_honour_on_gain_key",
      "kind": "suffix",
      "template": "Restore # Honour on picking up a Key",
      "tiers": [
        {
          "drop_chance": 0,
          "level": 1,
          "name": "of Donation",
          "text": "Restore (25—35) Honour on picking up a Key"
        },
        {
          "drop_chance": 0,
          "level": 45,
          "name": "of Offering",
          "text": "Restore (30—39) Honour on picking up a Key"
        },
        {
          "drop_chance": 0,
          "level": 60,
          "name": "of Entrusting",
          "text": "Restore (40—49) Honour on picking up a Key"
        },
        {
          "drop_chance": 0,
          "level": 72,
          "name": "of Bestowing",
          "text": "Restore (50—59) Honour on picking up a Key"
        },
        {
          "drop_chance": 0,
          "level": 78,
          "name": "of Bequeathing",
          "text": "Restore (60—75) Honour on picking up a Key"
        }
      ]
    },
    {
      "family_key": "SanctumResolveOnRoomComplete",
      "id": 529,
      "identifier": "sanctum_restore_honour_on_room_completion",
      "kind": "suffix",
      "template": "Restore # Honour on room completion",
      "tiers": [
        {
          "drop_chance": 0,
          "level": 60,
          "name": "of Progress",
          "text": "Restore (10—14) Honour on room completion"
        },
        {
          "drop_chance": 0,
          "level": 70,
          "name": "of Advancement",
          "text": "Restore (15—19) Honour on room completion"
        },
        {
          "drop_chance": 0,
          "level": 75,
          "name": "of Headway",
          "text": "Restore (20—24) Honour on room completion"
        },
        {
          "drop_chance": 0,
          "level": 80,
          "name": "of Betterment",
          "text": "Restore (25—30) Honour on room completion"
        }
      ]
    }
  ],
  "category": "Relics",
  "label": "Vase Relic",
  "slug": "Vase_Relic"
}